shapefileimport/__init__.py
shapefileimport/admin.py
shapefileimport/apps.py
shapefileimport/models.py
shapefileimport/shapetasks.py
shapefileimport/tests.py
shapefileimport/views.py
shapefileimport/migrations/__init__.py
django_shapefileimport-1.0.dist-info/LICENSE
django_shapefileimport-1.0.dist-info/METADATA
django_shapefileimport-1.0.dist-info/WHEEL
django_shapefileimport-1.0.dist-info/top_level.txt
django_shapefileimport-1.0.dist-info/RECORD
